Metadata-Version: 1.1
Name: qtgui
Version: 0.0.2a3
Summary: python3 pyqt wraper
Home-page: UNKNOWN
Author: Huang tao
Author-email: huangtao.jh@gmail.com
License: GPL
Platform: any
Requires: pyqt3_pyqt5
